contact_local/__init__.py
contact_local/contact.py
contact_local/contact_constants.py
contact_local/contact_local.py
contact_local/contacts_local_exceptions.py
contact_local-0.0.71.dist-info/METADATA
contact_local-0.0.71.dist-info/WHEEL
contact_local-0.0.71.dist-info/top_level.txt
contact_local-0.0.71.dist-info/RECORD
