Metadata-Version: 2.2
Name: contact-local
Version: 0.0.71
Summary: PyPI Package for Circles contact-local Local/Remote Python
Home-page: https://github.com/circles-zone/contact-local-python-package
Author: Circlez
Author-email: info@circlez.ai
Classifier: Programming Language :: Python :: 3
Classifier: License :: Other/Proprietary License
Classifier: Operating System :: OS Independent
Requires-Dist: logger-local>=0.0.140
Requires-Dist: database-mysql-local>=0.0.304
Requires-Dist: person-local>=0.0.61
Requires-Dist: multidict>=6.0.5
Dynamic: author
Dynamic: author-email
Dynamic: classifier
Dynamic: description
Dynamic: description-content-type
Dynamic: home-page
Dynamic: requires-dist
Dynamic: summary
